[
  {
    "id": "f_csv_e4310cda5b",
    "slug": "to-dream-is-to-allow-our-subconscious-thoughts-exceed-our-limitations",
    "texto": "To dream is to allow our subconscious thoughts exceed our limitations",
    "autor": "A-Lo",
    "autorSlug": "a-lo",
    "explicacao": "Citação de A-Lo sobre temas ligados a motivacao. “To dream is to allow our subconscious thoughts exceed our limitations” articula motivacao, dreamers, dreaming em registro de motivacao, com relevância para contextos como inspiracao e dreaming.",
    "semantica": {
      "categoriaPrincipal": "motivacao",
      "categorias": [
        "motivacao",
        "dreamers",
        "dreaming",
        "inspirational-quotes",
        "vida"
      ],
      "contextos": [
        "inspiracao",
        "dreaming",
        "inspirational-quotes",
        "vida",
        "life-and-living"
      ],
      "emocoes": [],
      "temas": [
        "motivacao",
        "dreamers",
        "dreaming",
        "inspirational-quotes",
        "dream",
        "allow",
        "subconscious",
        "thoughts"
      ],
      "palavrasChave": [
        "dreamers",
        "dreaming",
        "inspirational-quotes",
        "vida",
        "life-and-living",
        "subconscious",
        "subconscious-mind",
        "motivacao",
        "inspiracao"
      ],
      "tagsSeo": [
        "motivacao",
        "dreamers",
        "dreaming",
        "inspirational-quotes",
        "vida",
        "inspiracao",
        "life-and-living",
        "a-lo"
      ],
      "idiomaOriginal": "en",
      "ano": null,
      "periodoHistorico": null,
      "nacionalidadeAutor": null,
      "nascimentoAutor": null,
      "falecimentoAutor": null,
      "tipoAutor": null,
      "popularidade": 40,
      "fonte": null,
      "ultimaAtualizacao": "2026-06-01",
      "frasesRelacionadas": [
        "motivacao",
        "dreamers",
        "dreaming",
        "inspirational-quotes",
        "dream",
        "allow"
      ],
      "biografiaAutorCurta": null
    },
    "seo": {
      "titleSeo": "\"To dream is to allow our subconscious thoughts excee…\" — A-Lo | Metamensagem",
      "descriptionSeo": "Citação de A-Lo sobre temas ligados a motivacao. “To dream is to allow our subconscious thoughts exceed our limitations” articula motivacao, dreamers, dreamin…",
      "keywordsSeo": [
        "frases de A-Lo",
        "frases sobre motivacao",
        "frases motivacao",
        "frases dreamers",
        "frases inspiracao",
        "frases dreaming",
        "dreamers",
        "dreaming",
        "inspirational-quotes",
        "vida"
      ],
      "canonicalSlug": "to-dream-is-to-allow-our-subconscious-thoughts-exceed-our-limitations",
      "relatedKeywords": [
        "motivacao",
        "dreamers",
        "dreaming",
        "inspirational-quotes",
        "vida",
        "a-lo"
      ],
      "searchIntent": "informacional"
    },
    "frase_original": "To dream is to allow our subconscious thoughts exceed our limitations",
    "autor_original": "A-Lo",
    "autor_slug": "a-lo",
    "categoria": "motivacao",
    "contextos": [
      "inspiracao",
      "dreaming",
      "inspirational-quotes",
      "vida",
      "life-and-living"
    ],
    "palavras_chave": [
      "dreamers",
      "dreaming",
      "inspirational-quotes",
      "vida",
      "life-and-living",
      "subconscious",
      "subconscious-mind",
      "motivacao",
      "inspiracao"
    ],
    "ano_ou_data": null,
    "autor_tipo": null,
    "nacionalidade": null,
    "nascimento_falecimento": null,
    "fontes": null,
    "informacoes": {
      "ultima_atualizacao": "2026-06-01",
      "confiabilidade": "alta",
      "curadoria_ia": false,
      "enriquecimento_fase2": true
    }
  }
]
