[
  {
    "id": "f_csv_5b2556da25",
    "slug": "she-d-be-dead-before-the-memories-and-pain-were-finally-gone-she-knew-it-accep",
    "texto": "She'd be dead before the memories and pain were finally gone; she knew it, accepted it, and dealt with it.",
    "autor": "Catherine Coulter",
    "autorSlug": "catherine-coulter",
    "explicacao": "Citação de Catherine Coulter sobre temas ligados a familia. “She'd be dead before the memories and pain were finally gone; she knew it, accepted it, and dealt…” articula familia, memories, pain em registro de familia, com relevância para contextos como pain.",
    "semantica": {
      "categoriaPrincipal": "familia",
      "categorias": [
        "familia",
        "memories",
        "pain"
      ],
      "contextos": [
        "pain"
      ],
      "emocoes": [],
      "temas": [
        "familia",
        "memories",
        "pain",
        "before",
        "finally",
        "accepted",
        "dealt"
      ],
      "palavrasChave": [
        "memories",
        "pain",
        "familia"
      ],
      "tagsSeo": [
        "familia",
        "memories",
        "pain",
        "catherine-coulter"
      ],
      "idiomaOriginal": "en",
      "ano": null,
      "periodoHistorico": null,
      "nacionalidadeAutor": null,
      "nascimentoAutor": null,
      "falecimentoAutor": null,
      "tipoAutor": null,
      "popularidade": 34,
      "fonte": null,
      "ultimaAtualizacao": "2026-06-01",
      "frasesRelacionadas": [
        "familia",
        "memories",
        "pain",
        "before",
        "finally",
        "accepted"
      ],
      "biografiaAutorCurta": null
    },
    "seo": {
      "titleSeo": "\"She'd be dead before the memories and pain were fina…\" — Catherine Coulter | Metamensagem",
      "descriptionSeo": "Citação de Catherine Coulter sobre temas ligados a familia. “She'd be dead before the memories and pain were finally gone; she knew it, accepted it, and dealt…",
      "keywordsSeo": [
        "frases de Catherine Coulter",
        "frases sobre familia",
        "frases familia",
        "frases memories",
        "frases pain",
        "memories",
        "pain",
        "familia"
      ],
      "canonicalSlug": "she-d-be-dead-before-the-memories-and-pain-were-finally-gone-she-knew-it-accep",
      "relatedKeywords": [
        "familia",
        "memories",
        "pain",
        "catherine-coulter"
      ],
      "searchIntent": "informacional"
    },
    "frase_original": "She'd be dead before the memories and pain were finally gone; she knew it, accepted it, and dealt with it.",
    "autor_original": "Catherine Coulter",
    "autor_slug": "catherine-coulter",
    "categoria": "familia",
    "contextos": [
      "pain"
    ],
    "palavras_chave": [
      "memories",
      "pain",
      "familia"
    ],
    "ano_ou_data": null,
    "autor_tipo": null,
    "nacionalidade": null,
    "nascimento_falecimento": null,
    "fontes": null,
    "informacoes": {
      "ultima_atualizacao": "2026-06-01",
      "confiabilidade": "alta",
      "curadoria_ia": false,
      "enriquecimento_fase2": true
    }
  },
  {
    "id": "f_csv_7202515aab",
    "slug": "words-or-fists-it-didn-t-matter-the-soul-was-still-shattered",
    "texto": "Words or fists, it didn't matter. The soul was still shattered.",
    "autor": "Catherine Coulter",
    "autorSlug": "catherine-coulter",
    "explicacao": "Citação de Catherine Coulter sobre temas ligados a reflexao. “Words or fists, it didn't matter. The soul was still shattered.” articula reflexao, words, fists em registro de reflexao, com relevância para contextos como reflexao.",
    "semantica": {
      "categoriaPrincipal": "reflexao",
      "categorias": [
        "reflexao",
        "words"
      ],
      "contextos": [
        "reflexao"
      ],
      "emocoes": [],
      "temas": [
        "reflexao",
        "words",
        "fists",
        "matter",
        "still",
        "shattered"
      ],
      "palavrasChave": [
        "words",
        "reflexao"
      ],
      "tagsSeo": [
        "reflexao",
        "words",
        "catherine-coulter"
      ],
      "idiomaOriginal": "en",
      "ano": null,
      "periodoHistorico": null,
      "nacionalidadeAutor": null,
      "nascimentoAutor": null,
      "falecimentoAutor": null,
      "tipoAutor": null,
      "popularidade": 30,
      "fonte": null,
      "ultimaAtualizacao": "2026-06-01",
      "frasesRelacionadas": [
        "reflexao",
        "words",
        "fists",
        "matter",
        "still",
        "shattered"
      ],
      "biografiaAutorCurta": null
    },
    "seo": {
      "titleSeo": "\"Words or fists, it didn't matter. The soul was still…\" — Catherine Coulter | Metamensagem",
      "descriptionSeo": "Citação de Catherine Coulter sobre temas ligados a reflexao. “Words or fists, it didn't matter. The soul was still shattered.” articula reflexao, words, fists…",
      "keywordsSeo": [
        "frases de Catherine Coulter",
        "frases sobre reflexao",
        "frases reflexao",
        "frases words",
        "words",
        "reflexao"
      ],
      "canonicalSlug": "words-or-fists-it-didn-t-matter-the-soul-was-still-shattered",
      "relatedKeywords": [
        "reflexao",
        "words",
        "catherine-coulter"
      ],
      "searchIntent": "informacional"
    },
    "frase_original": "Words or fists, it didn't matter. The soul was still shattered.",
    "autor_original": "Catherine Coulter",
    "autor_slug": "catherine-coulter",
    "categoria": "reflexao",
    "contextos": [
      "reflexao"
    ],
    "palavras_chave": [
      "words",
      "reflexao"
    ],
    "ano_ou_data": null,
    "autor_tipo": null,
    "nacionalidade": null,
    "nascimento_falecimento": null,
    "fontes": null,
    "informacoes": {
      "ultima_atualizacao": "2026-06-01",
      "confiabilidade": "alta",
      "curadoria_ia": false,
      "enriquecimento_fase2": true
    }
  },
  {
    "id": "f_csv_d68093b711",
    "slug": "you-know-a-cell-phone-s-like-a-guy-if-you-don-t-plug-him-in-every-night-charg",
    "texto": "You know, a cell phone's like a guy; if you don't plug him in every night, charge him good, you got nothing at all.",
    "autor": "Catherine Coulter",
    "autorSlug": "catherine-coulter",
    "explicacao": "Metáfora atribuída a Catherine Coulter: compara elementos do cotidiano para falar de limites e escolhas conscientes. O trecho “You know, a cell phone's like a guy; if you don't plug him in every night, charge him good, you g…” usa imagem concreta para lembrar que reflexao, cell-phones, men pedem movimento e interpretação pessoal, em tom de boa-noite e reflexao-noturna.",
    "semantica": {
      "categoriaPrincipal": "reflexao",
      "categorias": [
        "reflexao",
        "cell-phones",
        "men",
        "sex",
        "simile"
      ],
      "contextos": [
        "boa-noite",
        "reflexao-noturna",
        "men",
        "sex",
        "simile"
      ],
      "emocoes": [],
      "temas": [
        "reflexao",
        "cell-phones",
        "men",
        "sex",
        "phone",
        "every",
        "night",
        "charge"
      ],
      "palavrasChave": [
        "cell-phones",
        "men",
        "sex",
        "simile",
        "telephones",
        "reflexao",
        "boa-noite",
        "reflexao-noturna"
      ],
      "tagsSeo": [
        "reflexao",
        "cell-phones",
        "men",
        "sex",
        "simile",
        "boa-noite",
        "reflexao-noturna",
        "catherine-coulter"
      ],
      "idiomaOriginal": "en",
      "ano": null,
      "periodoHistorico": null,
      "nacionalidadeAutor": null,
      "nascimentoAutor": null,
      "falecimentoAutor": null,
      "tipoAutor": null,
      "popularidade": 41,
      "fonte": null,
      "ultimaAtualizacao": "2026-06-01",
      "frasesRelacionadas": [
        "reflexao",
        "cell-phones",
        "men",
        "sex",
        "phone",
        "every"
      ],
      "biografiaAutorCurta": null
    },
    "seo": {
      "titleSeo": "\"You know, a cell phone's like a guy; if you don't pl…\" — Catherine Coulter | Metamensagem",
      "descriptionSeo": "Metáfora atribuída a Catherine Coulter: compara elementos do cotidiano para falar de limites e escolhas conscientes. O trecho “You know, a cell phone's like a…",
      "keywordsSeo": [
        "frases de Catherine Coulter",
        "frases sobre reflexao",
        "frases reflexao",
        "frases cell phones",
        "frases boa noite",
        "frases reflexao noturna",
        "cell-phones",
        "men",
        "sex",
        "simile"
      ],
      "canonicalSlug": "you-know-a-cell-phone-s-like-a-guy-if-you-don-t-plug-him-in-every-night-charg",
      "relatedKeywords": [
        "reflexao",
        "cell-phones",
        "men",
        "sex",
        "simile",
        "catherine-coulter"
      ],
      "searchIntent": "informacional"
    },
    "frase_original": "You know, a cell phone's like a guy; if you don't plug him in every night, charge him good, you got nothing at all.",
    "autor_original": "Catherine Coulter",
    "autor_slug": "catherine-coulter",
    "categoria": "reflexao",
    "contextos": [
      "boa-noite",
      "reflexao-noturna",
      "men",
      "sex",
      "simile"
    ],
    "palavras_chave": [
      "cell-phones",
      "men",
      "sex",
      "simile",
      "telephones",
      "reflexao",
      "boa-noite",
      "reflexao-noturna"
    ],
    "ano_ou_data": null,
    "autor_tipo": null,
    "nacionalidade": null,
    "nascimento_falecimento": null,
    "fontes": null,
    "informacoes": {
      "ultima_atualizacao": "2026-06-01",
      "confiabilidade": "alta",
      "curadoria_ia": false,
      "enriquecimento_fase2": true
    }
  },
  {
    "id": "f_csv_f139249496",
    "slug": "dear-god-i-must-be-dead-and-in-hell-since-you-re-here",
    "texto": "Dear God, I must be dead and in hell since you're here.",
    "autor": "Catherine Coulter",
    "autorSlug": "catherine-coulter",
    "explicacao": "Orientação direta de Catherine Coulter sobre temas ligados a fe. A afirmação “Dear God, I must be dead and in hell since you're here.” funciona como lembrete prático ligado a fe, dead, dislike, útil em momentos de dislike e hatred.",
    "semantica": {
      "categoriaPrincipal": "fe",
      "categorias": [
        "fe",
        "dead",
        "dislike",
        "hatred",
        "hell"
      ],
      "contextos": [
        "dislike",
        "hatred",
        "hell"
      ],
      "emocoes": [],
      "temas": [
        "fe",
        "dead",
        "dislike",
        "hatred",
        "since"
      ],
      "palavrasChave": [
        "dead",
        "dislike",
        "hatred",
        "hell",
        "fe"
      ],
      "tagsSeo": [
        "fe",
        "dead",
        "dislike",
        "hatred",
        "hell",
        "catherine-coulter"
      ],
      "idiomaOriginal": "en",
      "ano": null,
      "periodoHistorico": null,
      "nacionalidadeAutor": null,
      "nascimentoAutor": null,
      "falecimentoAutor": null,
      "tipoAutor": null,
      "popularidade": 33,
      "fonte": null,
      "ultimaAtualizacao": "2026-06-01",
      "frasesRelacionadas": [
        "fe",
        "dead",
        "dislike",
        "hatred",
        "since",
        "fe"
      ],
      "biografiaAutorCurta": null
    },
    "seo": {
      "titleSeo": "\"Dear God, I must be dead and in hell since you're here.\" — Catherine Coulter | Metamensagem",
      "descriptionSeo": "Orientação direta de Catherine Coulter sobre temas ligados a fe. A afirmação “Dear God, I must be dead and in hell since you're here.” funciona como lembrete…",
      "keywordsSeo": [
        "frases de Catherine Coulter",
        "frases sobre fe",
        "frases fe",
        "frases dead",
        "frases dislike",
        "frases hatred",
        "dead",
        "dislike",
        "hatred",
        "hell"
      ],
      "canonicalSlug": "dear-god-i-must-be-dead-and-in-hell-since-you-re-here",
      "relatedKeywords": [
        "fe",
        "dead",
        "dislike",
        "hatred",
        "hell",
        "catherine-coulter"
      ],
      "searchIntent": "informacional"
    },
    "frase_original": "Dear God, I must be dead and in hell since you're here.",
    "autor_original": "Catherine Coulter",
    "autor_slug": "catherine-coulter",
    "categoria": "fe",
    "contextos": [
      "dislike",
      "hatred",
      "hell"
    ],
    "palavras_chave": [
      "dead",
      "dislike",
      "hatred",
      "hell",
      "fe"
    ],
    "ano_ou_data": null,
    "autor_tipo": null,
    "nacionalidade": null,
    "nascimento_falecimento": null,
    "fontes": null,
    "informacoes": {
      "ultima_atualizacao": "2026-06-01",
      "confiabilidade": "alta",
      "curadoria_ia": false,
      "enriquecimento_fase2": true
    }
  }
]
