[
  {
    "id": "f_csv_78d2cde6fc",
    "slug": "a-bostonian-an-american-broadly-speaking",
    "texto": "A Bostonian - an American broadly speaking.",
    "autor": "G. E. Woodberry",
    "autorSlug": "g-e-woodberry",
    "explicacao": "Citação de G. E. Woodberry sobre temas ligados a reflexao. “A Bostonian - an American broadly speaking.” articula reflexao, america, americans em registro de reflexao, com relevância para contextos como viagem e americans.",
    "semantica": {
      "categoriaPrincipal": "reflexao",
      "categorias": [
        "reflexao",
        "america",
        "americans"
      ],
      "contextos": [
        "viagem",
        "americans"
      ],
      "emocoes": [],
      "temas": [
        "reflexao",
        "america",
        "americans",
        "bostonian",
        "american",
        "broadly",
        "speaking"
      ],
      "palavrasChave": [
        "america",
        "americans",
        "reflexao",
        "viagem"
      ],
      "tagsSeo": [
        "reflexao",
        "america",
        "americans",
        "viagem",
        "g-e-woodberry"
      ],
      "idiomaOriginal": "en",
      "ano": null,
      "periodoHistorico": null,
      "nacionalidadeAutor": null,
      "nascimentoAutor": null,
      "falecimentoAutor": null,
      "tipoAutor": null,
      "popularidade": 28,
      "fonte": null,
      "ultimaAtualizacao": "2026-06-01",
      "frasesRelacionadas": [
        "reflexao",
        "america",
        "americans",
        "bostonian",
        "american",
        "broadly"
      ],
      "biografiaAutorCurta": null
    },
    "seo": {
      "titleSeo": "\"A Bostonian - an American broadly speaking.\" — G. E. Woodberry | Metamensagem",
      "descriptionSeo": "Citação de G. E. Woodberry sobre temas ligados a reflexao. “A Bostonian - an American broadly speaking.” articula reflexao, america, americans em registro de…",
      "keywordsSeo": [
        "frases de G. E. Woodberry",
        "frases sobre reflexao",
        "frases reflexao",
        "frases america",
        "frases viagem",
        "frases americans",
        "america",
        "americans",
        "reflexao",
        "viagem"
      ],
      "canonicalSlug": "a-bostonian-an-american-broadly-speaking",
      "relatedKeywords": [
        "reflexao",
        "america",
        "americans",
        "g-e-woodberry"
      ],
      "searchIntent": "informacional"
    },
    "frase_original": "A Bostonian - an American broadly speaking.",
    "autor_original": "G. E. Woodberry",
    "autor_slug": "g-e-woodberry",
    "categoria": "reflexao",
    "contextos": [
      "viagem",
      "americans"
    ],
    "palavras_chave": [
      "america",
      "americans",
      "reflexao",
      "viagem"
    ],
    "ano_ou_data": null,
    "autor_tipo": null,
    "nacionalidade": null,
    "nascimento_falecimento": null,
    "fontes": null,
    "informacoes": {
      "ultima_atualizacao": "2026-06-01",
      "confiabilidade": "alta",
      "curadoria_ia": false,
      "enriquecimento_fase2": true
    }
  }
]
