[
  {
    "id": "f_csv_0065a535a3",
    "slug": "to-tell-a-ghost-story-means-being-willing-to-be-haunted",
    "texto": "To tell a ghost story means being willing to be haunted.",
    "autor": "Judith \"Jack\" Halberstam",
    "autorSlug": "judith-jack-halberstam",
    "explicacao": "Citação de Judith \"Jack\" Halberstam sobre temas ligados a reflexao. “To tell a ghost story means being willing to be haunted.” articula reflexao, accountability, ghost-stories em registro de reflexao, com relevância para contextos como ghost-stories e history.",
    "semantica": {
      "categoriaPrincipal": "reflexao",
      "categorias": [
        "reflexao",
        "accountability",
        "ghost-stories",
        "history",
        "queer-theory"
      ],
      "contextos": [
        "ghost-stories",
        "history",
        "queer-theory",
        "stories"
      ],
      "emocoes": [],
      "temas": [
        "reflexao",
        "accountability",
        "ghost-stories",
        "history",
        "ghost",
        "story",
        "means",
        "being"
      ],
      "palavrasChave": [
        "accountability",
        "ghost-stories",
        "history",
        "queer-theory",
        "stories",
        "reflexao"
      ],
      "tagsSeo": [
        "reflexao",
        "accountability",
        "ghost-stories",
        "history",
        "queer-theory",
        "stories",
        "judith-jack-halberstam"
      ],
      "idiomaOriginal": "en",
      "ano": null,
      "periodoHistorico": null,
      "nacionalidadeAutor": null,
      "nascimentoAutor": null,
      "falecimentoAutor": null,
      "tipoAutor": null,
      "popularidade": 35,
      "fonte": null,
      "ultimaAtualizacao": "2026-06-01",
      "frasesRelacionadas": [
        "reflexao",
        "accountability",
        "ghost-stories",
        "history",
        "ghost",
        "story"
      ],
      "biografiaAutorCurta": null
    },
    "seo": {
      "titleSeo": "\"To tell a ghost story means being willing to be haun…\" — Judith \"Jack\" Halberstam | Metamensagem",
      "descriptionSeo": "Citação de Judith \"Jack\" Halberstam sobre temas ligados a reflexao. “To tell a ghost story means being willing to be haunted.” articula reflexao, accountabili…",
      "keywordsSeo": [
        "frases de Judith \"Jack\" Halberstam",
        "frases sobre reflexao",
        "frases reflexao",
        "frases accountability",
        "frases ghost stories",
        "frases history",
        "accountability",
        "ghost-stories",
        "history",
        "queer-theory"
      ],
      "canonicalSlug": "to-tell-a-ghost-story-means-being-willing-to-be-haunted",
      "relatedKeywords": [
        "reflexao",
        "accountability",
        "ghost-stories",
        "history",
        "queer-theory",
        "judith-jack-halberstam"
      ],
      "searchIntent": "informacional"
    },
    "frase_original": "To tell a ghost story means being willing to be haunted.",
    "autor_original": "Judith \"Jack\" Halberstam",
    "autor_slug": "judith-jack-halberstam",
    "categoria": "reflexao",
    "contextos": [
      "ghost-stories",
      "history",
      "queer-theory",
      "stories"
    ],
    "palavras_chave": [
      "accountability",
      "ghost-stories",
      "history",
      "queer-theory",
      "stories",
      "reflexao"
    ],
    "ano_ou_data": null,
    "autor_tipo": null,
    "nacionalidade": null,
    "nascimento_falecimento": null,
    "fontes": null,
    "informacoes": {
      "ultima_atualizacao": "2026-06-01",
      "confiabilidade": "alta",
      "curadoria_ia": false,
      "enriquecimento_fase2": true
    }
  }
]
