[
  {
    "id": "f_csv_d7bc1b5e8e",
    "slug": "nik-loved-the-library-but-it-went-beyond-the-books-he-enjoyed-the-solitude-in",
    "texto": "Nik loved the library, but it went beyond the books; he enjoyed the solitude. In the library, nobody expected him to be strong, or brave, or daring. No need for wrestling to prove he was tougher, no showing teeth to keep other kids from thinking they could get the better of him.",
    "autor": "Liv Rider",
    "autorSlug": "liv-rider",
    "explicacao": "Citação de Liv Rider sobre vínculos afetivos e cuidado mútuo. “Nik loved the library, but it went beyond the books; he enjoyed the solitude. In the library, nob…” articula reflexao, librarians, libraries em registro de reflexao, com relevância para contextos como libraries e library.",
    "semantica": {
      "categoriaPrincipal": "reflexao",
      "categorias": [
        "reflexao",
        "librarians",
        "libraries",
        "library"
      ],
      "contextos": [
        "libraries",
        "library"
      ],
      "emocoes": [
        "coragem",
        "alegria",
        "amor"
      ],
      "temas": [
        "reflexao",
        "librarians",
        "libraries",
        "library",
        "loved",
        "beyond",
        "books",
        "enjoyed"
      ],
      "palavrasChave": [
        "librarians",
        "libraries",
        "library",
        "reflexao",
        "coragem",
        "alegria",
        "amor"
      ],
      "tagsSeo": [
        "reflexao",
        "librarians",
        "libraries",
        "library",
        "coragem",
        "alegria",
        "amor",
        "liv-rider"
      ],
      "idiomaOriginal": "en",
      "ano": null,
      "periodoHistorico": null,
      "nacionalidadeAutor": null,
      "nascimentoAutor": null,
      "falecimentoAutor": null,
      "tipoAutor": null,
      "popularidade": 53,
      "fonte": null,
      "ultimaAtualizacao": "2026-06-01",
      "frasesRelacionadas": [
        "reflexao",
        "librarians",
        "libraries",
        "library",
        "loved",
        "beyond"
      ],
      "biografiaAutorCurta": null
    },
    "seo": {
      "titleSeo": "\"Nik loved the library, but it went beyond the books;…\" — Liv Rider | Metamensagem",
      "descriptionSeo": "Citação de Liv Rider sobre vínculos afetivos e cuidado mútuo. “Nik loved the library, but it went beyond the books; he enjoyed the solitude. In the library, n…",
      "keywordsSeo": [
        "frases de Liv Rider",
        "frases sobre reflexao",
        "frases reflexao",
        "frases librarians",
        "frases libraries",
        "frases library",
        "librarians",
        "libraries",
        "library",
        "reflexao"
      ],
      "canonicalSlug": "nik-loved-the-library-but-it-went-beyond-the-books-he-enjoyed-the-solitude-in",
      "relatedKeywords": [
        "coragem",
        "alegria",
        "amor",
        "reflexao",
        "librarians",
        "libraries",
        "library",
        "liv-rider"
      ],
      "searchIntent": "informacional"
    },
    "frase_original": "Nik loved the library, but it went beyond the books; he enjoyed the solitude. In the library, nobody expected him to be strong, or brave, or daring. No need for wrestling to prove he was tougher, no showing teeth to keep other kids from thinking they could get the better of him.",
    "autor_original": "Liv Rider",
    "autor_slug": "liv-rider",
    "categoria": "reflexao",
    "contextos": [
      "libraries",
      "library"
    ],
    "palavras_chave": [
      "librarians",
      "libraries",
      "library",
      "reflexao",
      "coragem",
      "alegria",
      "amor"
    ],
    "ano_ou_data": null,
    "autor_tipo": null,
    "nacionalidade": null,
    "nascimento_falecimento": null,
    "fontes": null,
    "informacoes": {
      "ultima_atualizacao": "2026-06-01",
      "confiabilidade": "alta",
      "curadoria_ia": false,
      "enriquecimento_fase2": true
    }
  }
]
