[
  {
    "id": "f_csv_69c89e5ca7",
    "slug": "nature-is-another-name-for-the-miracles-that-are-so-commonplace-in-our-lives-th",
    "texto": "Nature\" is another name for the miracles that are so commonplace in our lives that we take for granted and have grown used to seeing them.",
    "autor": "Shalom Arush",
    "autorSlug": "shalom-arush",
    "explicacao": "Citação de Shalom Arush sobre sentido da existência e experiência vivida. “Nature\" is another name for the miracles that are so commonplace in our lives that we take for gr…” articula fe, faith, miracle em registro de fe, com relevância para contextos como miracle e nature.",
    "semantica": {
      "categoriaPrincipal": "fe",
      "categorias": [
        "fe",
        "faith",
        "miracle",
        "nature"
      ],
      "contextos": [
        "miracle",
        "nature"
      ],
      "emocoes": [],
      "temas": [
        "fe",
        "faith",
        "miracle",
        "nature",
        "another",
        "miracles",
        "commonplace",
        "lives"
      ],
      "palavrasChave": [
        "faith",
        "miracle",
        "nature",
        "fe"
      ],
      "tagsSeo": [
        "fe",
        "faith",
        "miracle",
        "nature",
        "shalom-arush"
      ],
      "idiomaOriginal": "en",
      "ano": null,
      "periodoHistorico": null,
      "nacionalidadeAutor": null,
      "nascimentoAutor": null,
      "falecimentoAutor": null,
      "tipoAutor": null,
      "popularidade": 39,
      "fonte": null,
      "ultimaAtualizacao": "2026-06-01",
      "frasesRelacionadas": [
        "fe",
        "faith",
        "miracle",
        "nature",
        "another",
        "miracles"
      ],
      "biografiaAutorCurta": null
    },
    "seo": {
      "titleSeo": "\"Nature\" is another name for the miracles that are so…\" — Shalom Arush | Metamensagem",
      "descriptionSeo": "Citação de Shalom Arush sobre sentido da existência e experiência vivida. “Nature\" is another name for the miracles that are so commonplace in our lives that…",
      "keywordsSeo": [
        "frases de Shalom Arush",
        "frases sobre fe",
        "frases fe",
        "frases faith",
        "frases miracle",
        "frases nature",
        "faith",
        "miracle",
        "nature",
        "fe"
      ],
      "canonicalSlug": "nature-is-another-name-for-the-miracles-that-are-so-commonplace-in-our-lives-th",
      "relatedKeywords": [
        "fe",
        "faith",
        "miracle",
        "nature",
        "shalom-arush"
      ],
      "searchIntent": "informacional"
    },
    "frase_original": "Nature\" is another name for the miracles that are so commonplace in our lives that we take for granted and have grown used to seeing them.",
    "autor_original": "Shalom Arush",
    "autor_slug": "shalom-arush",
    "categoria": "fe",
    "contextos": [
      "miracle",
      "nature"
    ],
    "palavras_chave": [
      "faith",
      "miracle",
      "nature",
      "fe"
    ],
    "ano_ou_data": null,
    "autor_tipo": null,
    "nacionalidade": null,
    "nascimento_falecimento": null,
    "fontes": null,
    "informacoes": {
      "ultima_atualizacao": "2026-06-01",
      "confiabilidade": "alta",
      "curadoria_ia": false,
      "enriquecimento_fase2": true
    }
  }
]
