[
  {
    "id": "f_csv_f44ce5ae3b",
    "slug": "it-seems-that-in-almost-all-societies-the-attitudes-that-people-have-to-languag",
    "texto": "It seems that in almost all societies, the attitudes that people have to language change is basically the same. People everywhere tend to say that the older form of a language is in some sense 'better' than the form that is being used today.",
    "autor": "Terry Crowley",
    "autorSlug": "terry-crowley",
    "explicacao": "Orientação direta de Terry Crowley sobre temas ligados a tempo. A afirmação “It seems that in almost all societies, the attitudes that people have to language change is basic…” funciona como lembrete prático ligado a tempo, change, language, útil em momentos de mudanca e termino.",
    "semantica": {
      "categoriaPrincipal": "tempo",
      "categorias": [
        "tempo",
        "change",
        "language",
        "linguistics"
      ],
      "contextos": [
        "mudanca",
        "termino",
        "language",
        "linguistics"
      ],
      "emocoes": [],
      "temas": [
        "tempo",
        "change",
        "language",
        "linguistics",
        "people",
        "seems",
        "almost",
        "societies"
      ],
      "palavrasChave": [
        "change",
        "language",
        "linguistics",
        "tempo",
        "mudanca",
        "termino"
      ],
      "tagsSeo": [
        "tempo",
        "change",
        "language",
        "linguistics",
        "mudanca",
        "termino",
        "terry-crowley"
      ],
      "idiomaOriginal": "en",
      "ano": null,
      "periodoHistorico": null,
      "nacionalidadeAutor": null,
      "nascimentoAutor": null,
      "falecimentoAutor": null,
      "tipoAutor": null,
      "popularidade": 50,
      "fonte": null,
      "ultimaAtualizacao": "2026-06-01",
      "frasesRelacionadas": [
        "tempo",
        "change",
        "language",
        "linguistics",
        "people",
        "seems"
      ],
      "biografiaAutorCurta": null
    },
    "seo": {
      "titleSeo": "\"It seems that in almost all societies, the attitudes…\" — Terry Crowley | Metamensagem",
      "descriptionSeo": "Orientação direta de Terry Crowley sobre temas ligados a tempo. A afirmação “It seems that in almost all societies, the attitudes that people have to language…",
      "keywordsSeo": [
        "frases de Terry Crowley",
        "frases sobre tempo",
        "frases tempo",
        "frases change",
        "frases mudanca",
        "frases termino",
        "change",
        "language",
        "linguistics",
        "tempo"
      ],
      "canonicalSlug": "it-seems-that-in-almost-all-societies-the-attitudes-that-people-have-to-languag",
      "relatedKeywords": [
        "tempo",
        "change",
        "language",
        "linguistics",
        "terry-crowley"
      ],
      "searchIntent": "informacional"
    },
    "frase_original": "It seems that in almost all societies, the attitudes that people have to language change is basically the same. People everywhere tend to say that the older form of a language is in some sense 'better' than the form that is being used today.",
    "autor_original": "Terry Crowley",
    "autor_slug": "terry-crowley",
    "categoria": "tempo",
    "contextos": [
      "mudanca",
      "termino",
      "language",
      "linguistics"
    ],
    "palavras_chave": [
      "change",
      "language",
      "linguistics",
      "tempo",
      "mudanca",
      "termino"
    ],
    "ano_ou_data": null,
    "autor_tipo": null,
    "nacionalidade": null,
    "nascimento_falecimento": null,
    "fontes": null,
    "informacoes": {
      "ultima_atualizacao": "2026-06-01",
      "confiabilidade": "alta",
      "curadoria_ia": false,
      "enriquecimento_fase2": true
    }
  }
]
